eigentune/__init__.py
eigentune/config.py
eigentune/layer.py
eigentune/model.py
eigentune-0.1.0.dist-info/licenses/LICENSE
eigentune-0.1.0.dist-info/METADATA
eigentune-0.1.0.dist-info/WHEEL
eigentune-0.1.0.dist-info/top_level.txt
eigentune-0.1.0.dist-info/RECORD
