Metadata-Version: 2.4
Name: eigentune
Version: 0.1.0
Summary: EigenTune: An extremely parameter-efficient fine-tuning method via singular value scaling.
Author-email: MrAnayDongre <dongreana@gmail.com>
License: 
Project-URL: Homepage, https://github.com/MrAnayDongre/eigentune
Project-URL: Bug Tracker, https://github.com/MrAnayDongre/eigentune/issues
Classifier: Development Status :: 4 - Beta
Classifier: Programming Language :: Python :: 3
Classifier: License :: OSI Approved :: Apache Software License
Classifier: Operating System :: OS Independent
Classifier: Intended Audience :: Science/Research
Classifier: Topic :: Scientific/Engineering :: Artificial Intelligence
Classifier: Topic :: Software Development :: Libraries :: Python Modules
Requires-Python: >=3.8
License-File: LICENSE
Requires-Dist: torch>=2.0.0
Requires-Dist: peft>=0.8.0
Dynamic: license-file
